[
  {
    "context": "Workspace",
    "bindings": {
      "f5": ["task::Spawn", { "task_name": "Run Lua Script" }],
      "f6": ["task::Spawn", { "task_name": "Run Love2D Project" }],
      "ctrl-f5": "debugger::Rerun",
      "ctrl-alt-f5": "debugger::Continue"
    }
  },

  {
    "context": "Editor && vim_mode == insert",
    "bindings": {}
  },

  {
    "context": "(Workspace && debugger_stopped)",
    "bindings": {
      "ctrl-f6": "debugger::Pause"
    }
  },
  {
    "bindings": {
      "ctrl-alt-o": "snippets::OpenFolder"
    }
  },
  {
    "bindings": {
      "ctrl-shift-o": "workspace::Open"
    }
  },
  {
    "bindings": {
      "ctrl-alt-n": "editor::ToggleRelativeLineNumbers"
    }
  }
]
